pycodar/__init__.py
pycodar/analyze.py
pycodar/cli.py
pycodar-0.1.7.dist-info/METADATA
pycodar-0.1.7.dist-info/WHEEL
pycodar-0.1.7.dist-info/entry_points.txt
pycodar-0.1.7.dist-info/top_level.txt
pycodar-0.1.7.dist-info/RECORD
