Metadata-Version: 2.4
Name: pycodar
Version: 0.1.7
Summary: A simple tool for auditing and understanding your codebase.
Home-page: https://github.com/QuentinWach/pycodar
Author: Quentin Wach
Author-email: Quentin Wach <quentin.wach@gmail.com>
License: MIT
Project-URL: Homepage, https://github.com/QuentinWach/pycodar
Project-URL: Documentation, https://github.com/QuentinWach/pycodar#readme
Project-URL: Bug-Tracker, https://github.com/QuentinWach/pycodar/issues
Keywords: code-analysis,architecture,metrics,codebase,development-tools
Classifier: Development Status :: 4 - Beta
Classifier: Programming Language :: Python :: 3
Classifier: Programming Language :: Python :: 3.6
Classifier: Programming Language :: Python :: 3.7
Classifier: Programming Language :: Python :: 3.8
Classifier: Programming Language :: Python :: 3.9
Classifier: Programming Language :: Python :: 3.10
Classifier: Programming Language :: Python :: 3.11
Classifier: License :: OSI Approved :: MIT License
Classifier: Operating System :: OS Independent
Classifier: Topic :: Software Development :: Libraries :: Python Modules
Classifier: Topic :: Software Development :: Quality Assurance
Classifier: Intended Audience :: Developers
Requires-Python: >=3.6
Requires-Dist: rich>=10.0.0
Requires-Dist: typer>=0.9.0
Requires-Dist: pathspec>=0.11.0
Dynamic: author
Dynamic: home-page
Dynamic: requires-python
